README.md
setup.py
artiftest.egg-info/PKG-INFO
artiftest.egg-info/SOURCES.txt
artiftest.egg-info/dependency_links.txt
artiftest.egg-info/entry_points.txt
artiftest.egg-info/requires.txt
artiftest.egg-info/top_level.txt
mlflow_databricks_artifacts/__init__.py
mlflow_databricks_artifacts/azure/__init__.py
mlflow_databricks_artifacts/azure/client.py
mlflow_databricks_artifacts/protos/__init__.py
mlflow_databricks_artifacts/protos/databricks_artifacts_pb2.py
mlflow_databricks_artifacts/protos/databricks_pb2.py
mlflow_databricks_artifacts/protos/scalapb/__init__.py
mlflow_databricks_artifacts/protos/scalapb/scalapb_pb2.py
mlflow_databricks_artifacts/store/__init__.py
mlflow_databricks_artifacts/store/artifact_repo.py
mlflow_databricks_artifacts/store/entrypoint.py
mlflow_databricks_artifacts/utils/__init__.py
mlflow_databricks_artifacts/utils/databricks_utils.py
mlflow_databricks_artifacts/utils/file_utils.py
mlflow_databricks_artifacts/utils/proto_json_utils.py
mlflow_databricks_artifacts/utils/rest_utils.py
mlflow_databricks_artifacts/utils/string_utils.py
mlflow_databricks_artifacts/utils/uri.py