Metadata-Version: 2.1
Name: artiftest
Version: 1.0.0
Summary: Plugin to create and access MLflow-managed artifacts on Databricks
Home-page: UNKNOWN
Author: Databricks
License: UNKNOWN
Platform: UNKNOWN
